gctele_iq/__init__.py
gctele_iq/evaluation/__init__.py
gctele_iq/evaluation/compute_metrics.py
gctele_iq/evaluation/compute_metrics_LLM.py
gctele_iq/evaluation/compute_scores.py
gctele_iq/evaluation/eval_prompt/__init__.py
gctele_iq/evaluation/eval_prompt/ac.py
gctele_iq/evaluation/eval_prompt/cs.py
gctele_iq/evaluation/eval_prompt/os.py
gctele_iq/evaluation/eval_prompt/qa.py
gctele_iq/generation/__init__.py
gctele_iq/generation/generator_api.py
gctele_iq/generation/generator_local.py
gctele_iq/generation/prompt_configs/CSQ.py
gctele_iq/generation/prompt_configs/MCQ.py
gctele_iq/generation/prompt_configs/QA.py
gctele_iq/generation/prompt_configs/SCQ.py
gctele_iq/generation/prompt_configs/TFQ.py
gctele_iq/generation/prompt_configs/__init__.py
gctele_iq/models/Baichuan.py
gctele_iq/models/GLM.py
gctele_iq/models/Gemma.py
gctele_iq/models/Jiutian.py
gctele_iq/models/Llama.py
gctele_iq/models/Minicpm.py
gctele_iq/models/Qwen.py
gctele_iq/models/Qwen3.py
gctele_iq/models/Telechat.py
gctele_iq/models/Yi.py
gctele_iq/models/__init__.py
gctele_iq/models/pangu.py
gctele_iq/models/test.py
gctele_iq/utils/__init__.py
gctele_iq/utils/data_helper.py
gctele_iq/visualization/__init__.py
gctele_iq/visualization/compute_ranking_average.py
gctele_iq/visualization/compute_ranking_single.py
gctele_iq-0.1.6.dist-info/METADATA
gctele_iq-0.1.6.dist-info/WHEEL
gctele_iq-0.1.6.dist-info/top_level.txt
gctele_iq-0.1.6.dist-info/RECORD
